albumentationsxl/__init__.py
albumentationsxl/augmentations/__init__.py
albumentationsxl/augmentations/functional/__init__.py
albumentationsxl/augmentations/functional/blur.py
albumentationsxl/augmentations/functional/color.py
albumentationsxl/augmentations/functional/crops.py
albumentationsxl/augmentations/functional/dropout.py
albumentationsxl/augmentations/functional/geometric.py
albumentationsxl/augmentations/functional/misc.py
albumentationsxl/augmentations/functional/pytorch.py
albumentationsxl/augmentations/functional/resizes.py
albumentationsxl/augmentations/transforms/__init__.py
albumentationsxl/augmentations/transforms/blur.py
albumentationsxl/augmentations/transforms/color.py
albumentationsxl/augmentations/transforms/crops.py
albumentationsxl/augmentations/transforms/dropout.py
albumentationsxl/augmentations/transforms/geometric.py
albumentationsxl/augmentations/transforms/misc.py
albumentationsxl/augmentations/transforms/pytorch.py
albumentationsxl/augmentations/transforms/resizes.py
albumentationsxl/augmentations/transforms/rotate.py
albumentationsxl/augmentations/utils.py
albumentationsxl/core/__init__.py
albumentationsxl/core/bbox_utils.py
albumentationsxl/core/composition.py
albumentationsxl/core/keypoints_utils.py
albumentationsxl/core/serialization.py
albumentationsxl/core/transforms_interface.py
albumentationsxl/core/utils.py
albumentationsxl/random_utils.py
albumentationsxl-0.1.2.dist-info/LICENSE
albumentationsxl-0.1.2.dist-info/METADATA
albumentationsxl-0.1.2.dist-info/WHEEL
albumentationsxl-0.1.2.dist-info/RECORD
