Metadata-Version: 2.3
Name: albumentationsxl
Version: 0.1.2
Summary: A pytohn library for large image augmentations
License: MIT
Author: Your Name
Author-email: you@example.com
Requires-Python: >=3.10,<4.0
Classifier: License :: OSI Approved :: MIT License
Classifier: Programming Language :: Python :: 3
Classifier: Programming Language :: Python :: 3.10
Classifier: Programming Language :: Python :: 3.11
Classifier: Programming Language :: Python :: 3.12
Classifier: Programming Language :: Python :: 3.13
Requires-Dist: numpy (>=1.23.5)
Requires-Dist: pyvips (>=2.2.1,<3.0.0)
Requires-Dist: scikit-image (>=0.20.0)
